{"cameraMode":{"drawMode":0,"name":"Shaded","section":"Shading Mode"},"sceneLighting":true,"audioPlay":false,"sceneViewState":{"m_AlwaysRefresh":false,"showFog":true,"showSkybox":true,"showFlares":true,"showImageEffects":true,"showParticleSystems":true,"showVisualEffectGraphs":true,"m_FxEnabled":true},"in2DMode":false,"pivot":{"x":1.4655710458755494,"y":1.482277512550354,"z":0.0864281877875328},"rotation":{"x":-0.1050330102443695,"y":0.76800936460495,"z":-0.130498006939888,"w":-0.6181425452232361},"size":5.185164451599121,"orthographic":false}